{
  "datetime": "2022-02-14T22:58:07Z",
  "opt_score": 0.3633333333333333,
  "opt_settings": [
    [
      [
        [
          -3.04229015199666,
          1.2456177141867322
        ]
      ]
    ],
    [
      [
        [
          1.0541655216886203
        ],
        [
          1.4760265324391213
        ]
      ],
      [
        [
          -0.27545841762057555
        ],
        [
          -2.1682706082234504
        ]
      ]
    ]
  ],
  "scores": [
    -0.08533333333333326,
    0.3633333333333333,
    0.6176666666666666,
    0.914,
    1.0763333333333331,
    1.2979999999999998,
    1.445,
    1.591,
    1.702,
    1.8996666666666666,
    1.9863333333333335,
    2.0683333333333334,
    2.1926666666666668,
    2.2503333333333333,
    2.333666666666667,
    2.3773333333333335,
    2.404333333333333
  ],
  "samples": [
    0,
    1,
    2,
    3,
    4,
    5,
    6,
    7,
    8,
    9,
    10,
    11,
    12,
    13,
    14,
    15,
    16
  ],
  "settings_history": [
    [
      [
        [
          [
            -2.9317501519966602,
            1.2456177141867322
          ]
        ]
      ],
      [
        [
          [
            1.1203055216886204
          ],
          [
            1.6329065324391214
          ]
        ],
        [
          [
            -0.3717384176205756
          ],
          [
            -2.2106506082234505
          ]
        ]
      ]
    ],
    [
      [
        [
          [
            -3.04229015199666,
            1.2456177141867322
          ]
        ]
      ],
      [
        [
          [
            1.0541655216886203
          ],
          [
            1.4760265324391213
          ]
        ],
        [
          [
            -0.27545841762057555
          ],
          [
            -2.1682706082234504
          ]
        ]
      ]
    ],
    [
      [
        [
          [
            -3.1224501519966603,
            1.2456177141867322
          ]
        ]
      ],
      [
        [
          [
            0.9947255216886204
          ],
          [
            1.3191665324391213
          ]
        ],
        [
          [
            -0.21695841762057555
          ],
          [
            -2.1328906082234504
          ]
        ]
      ]
    ],
    [
      [
        [
          [
            -3.1783101519966603,
            1.2456177141867322
          ]
        ]
      ],
      [
        [
          [
            0.9396855216886204
          ],
          [
            1.1692665324391214
          ]
        ],
        [
          [
            -0.18911841762057555
          ],
          [
            -2.1061506082234502
          ]
        ]
      ]
    ],
    [
      [
        [
          [
            -3.2229301519966604,
            1.2456177141867322
          ]
        ]
      ],
      [
        [
          [
            0.8938255216886204
          ],
          [
            1.0277465324391213
          ]
        ],
        [
          [
            -0.18087841762057555
          ],
          [
            -2.0863106082234504
          ]
        ]
      ]
    ],
    [
      [
        [
          [
            -3.2628501519966604,
            1.2456177141867322
          ]
        ]
      ],
      [
        [
          [
            0.8529255216886203
          ],
          [
            0.8922865324391213
          ]
        ],
        [
          [
            -0.18271841762057556
          ],
          [
            -2.0780706082234506
          ]
        ]
      ]
    ],
    [
      [
        [
          [
            -3.3079301519966604,
            1.2456177141867322
          ]
        ]
      ],
      [
        [
          [
            0.8200055216886204
          ],
          [
            0.7629865324391213
          ]
        ],
        [
          [
            -0.19483841762057555
          ],
          [
            -2.0764106082234504
          ]
        ]
      ]
    ],
    [
      [
        [
          [
            -3.36125015199666,
            1.2456177141867322
          ]
        ]
      ],
      [
        [
          [
            0.8003255216886204
          ],
          [
            0.6407465324391213
          ]
        ],
        [
          [
            -0.21101841762057555
          ],
          [
            -2.0804106082234504
          ]
        ]
      ]
    ],
    [
      [
        [
          [
            -3.4202501519966604,
            1.2456177141867322
          ]
        ]
      ],
      [
        [
          [
            0.7874655216886204
          ],
          [
            0.5308065324391213
          ]
        ],
        [
          [
            -0.23209841762057554
          ],
          [
            -2.0863706082234503
          ]
        ]
      ]
    ],
    [
      [
        [
          [
            -3.4842701519966606,
            1.2456177141867322
          ]
        ]
      ],
      [
        [
          [
            0.7876455216886203
          ],
          [
            0.42400653243912134
          ]
        ],
        [
          [
            -0.25953841762057556
          ],
          [
            -2.0966106082234504
          ]
        ]
      ]
    ],
    [
      [
        [
          [
            -3.5561301519966606,
            1.2456177141867322
          ]
        ]
      ],
      [
        [
          [
            0.8012255216886204
          ],
          [
            0.3276265324391213
          ]
        ],
        [
          [
            -0.28371841762057554
          ],
          [
            -2.10689060822345
          ]
        ]
      ]
    ],
    [
      [
        [
          [
            -3.6335301519966605,
            1.2456177141867322
          ]
        ]
      ],
      [
        [
          [
            0.8256255216886204
          ],
          [
            0.23820653243912132
          ]
        ],
        [
          [
            -0.3103384176205755
          ],
          [
            -2.1134106082234503
          ]
        ]
      ]
    ],
    [
      [
        [
          [
            -3.6964901519966604,
            1.2456177141867322
          ]
        ]
      ],
      [
        [
          [
            0.8579255216886204
          ],
          [
            0.1594865324391213
          ]
        ],
        [
          [
            -0.33455841762057553
          ],
          [
            -2.11813060822345
          ]
        ]
      ]
    ],
    [
      [
        [
          [
            -3.7593301519966604,
            1.2456177141867322
          ]
        ]
      ],
      [
        [
          [
            0.8931455216886204
          ],
          [
            0.09354653243912131
          ]
        ],
        [
          [
            -0.35471841762057554
          ],
          [
            -2.11753060822345
          ]
        ]
      ]
    ],
    [
      [
        [
          [
            -3.8018501519966605,
            1.2456177141867322
          ]
        ]
      ],
      [
        [
          [
            0.9337455216886204
          ],
          [
            0.03220653243912131
          ]
        ],
        [
          [
            -0.37469841762057554
          ],
          [
            -2.11527060822345
          ]
        ]
      ]
    ],
    [
      [
        [
          [
            -3.8299301519966606,
            1.2456177141867322
          ]
        ]
      ],
      [
        [
          [
            0.9728055216886203
          ],
          [
            -0.016373467560878686
          ]
        ],
        [
          [
            -0.38989841762057553
          ],
          [
            -2.11201060822345
          ]
        ]
      ]
    ],
    [
      [
        [
          [
            -3.857610151996661,
            1.2456177141867322
          ]
        ]
      ],
      [
        [
          [
            1.0085055216886203
          ],
          [
            -0.060513467560878685
          ]
        ],
        [
          [
            -0.4055784176205755
          ],
          [
            -2.10705060822345
          ]
        ]
      ]
    ]
  ],
  "step_times": [
    148.9849648475647,
    148.9849648475647,
    99.92315912246704,
    99.99078702926636,
    118.18207907676697,
    99.82186269760132,
    150.6927411556244,
    102.26995706558228,
    133.87732195854187,
    110.42169380187988,
    100.43912172317505,
    102.58092904090881,
    99.81272721290588,
    100.56806111335754,
    100.78345704078674,
    100.99544286727905,
    100.12182688713074
  ],
  "step_size": 0.12,
  "theoretical_score": 2.4726666666666666,
  "device_name": "qiskit.ibmq",
  "device_shots": 6000
}